funniest/__init__.py
funniestyi-0.1.dist-info/METADATA
funniestyi-0.1.dist-info/RECORD
funniestyi-0.1.dist-info/WHEEL
funniestyi-0.1.dist-info/top_level.txt
