Metadata-Version: 2.1
Name: funniestyi
Version: 0.1
Summary: The funniest joke in the world
Home-page: https://github.com/dymodi/machine_learning
Author: Flying Circus
Author-email: dymodi@gmail.com
License: MIT
Platform: UNKNOWN
